titanshield_cli/__init__.py
titanshield_cli/analyzer.py
titanshield_cli/decompiler.py
titanshield_cli/main.py
titanshield_cli/reporter.py
titanshield_cli/rule_engine.py
titanshield_cli-0.1.0.dist-info/METADATA
titanshield_cli-0.1.0.dist-info/WHEEL
titanshield_cli-0.1.0.dist-info/entry_points.txt
titanshield_cli-0.1.0.dist-info/top_level.txt
titanshield_cli-0.1.0.dist-info/RECORD
