Metadata-Version: 2.4
Name: titanshield-cli
Version: 0.1.0
Requires-Dist: pyaxmlparser
Requires-Dist: pyyaml
Requires-Dist: rich
Dynamic: requires-dist
